ditto/__init__.py
ditto/core/__init__.py
ditto/core/admin.py
ditto/core/app_settings.py
ditto/core/apps.py
ditto/core/managers.py
ditto/core/models.py
ditto/core/paginator.py
ditto/core/urls.py
ditto/core/views.py
ditto/core/management/commands/__init__.py
ditto/core/migrations/__init__.py
ditto/core/static/ditto-core/css/bootstrap.min.css
ditto/core/static/ditto-core/css/bootstrap.min.css.map
ditto/core/static/ditto-core/img/default_avatar.png
ditto/core/static/ditto-core/img/original_error.jpg
ditto/core/static/ditto-core/img/original_missing.jpg
ditto/core/static/ditto-core/js/jquery-3.5.1.slim.min.js
ditto/core/static/ditto-core/js/jquery-3.5.1.slim.min.map
ditto/core/static/ditto-core/js/popper.min.js
ditto/core/static/ditto-core/js/popper.min.js.map
ditto/core/static/ditto-core/js/bootstrap/carousel.js
ditto/core/static/ditto-core/js/bootstrap/carousel.js.map
ditto/core/static/ditto-core/js/bootstrap/collapse.js
ditto/core/static/ditto-core/js/bootstrap/collapse.js.map
ditto/core/static/ditto-core/js/bootstrap/util.js
ditto/core/static/ditto-core/js/bootstrap/util.js.map
ditto/core/templates/ditto/archive_day.html
ditto/core/templates/ditto/base.html
ditto/core/templates/ditto/home.html
ditto/core/templates/ditto/tag_detail.html
ditto/core/templates/ditto/tag_list.html
ditto/core/templates/ditto/includes/account_list.html
ditto/core/templates/ditto/includes/item_list.html
ditto/core/templates/ditto/includes/item_lists.html
ditto/core/templates/ditto/includes/pager.html
ditto/core/templates/ditto/includes/pagination.html
ditto/core/templates/ditto/includes/variety_nav.html
ditto/core/templatetags/__init__.py
ditto/core/templatetags/ditto_core.py
ditto/core/utils/__init__.py
ditto/core/utils/downloader.py
ditto/flickr/__init__.py
ditto/flickr/admin.py
ditto/flickr/app_settings.py
ditto/flickr/apps.py
ditto/flickr/checks.py
ditto/flickr/factories.py
ditto/flickr/imagegenerators.py
ditto/flickr/managers.py
ditto/flickr/models.py
ditto/flickr/urls.py
django_ditto-3.7.0.dist-info/licenses/LICENSE
django_ditto-3.7.0.dist-info/METADATA
django_ditto-3.7.0.dist-info/WHEEL
django_ditto-3.7.0.dist-info/top_level.txt
django_ditto-3.7.0.dist-info/RECORD
