Metadata-Version: 2.4
Name: django-ditto
Version: 3.7.0
Summary: A Django app to copy stuff from your accounts on Flickr, Last.fm, Pinboard and Twitter.
Author-email: Phil Gyford <phil@gyford.com>
License: The MIT License (MIT)
Project-URL: Changelog, https://github.com/philgyford/django-ditto/blob/main/CHANGELOG.md
Project-URL: Documentation, https://django-ditto.readthedocs.io/
Project-URL: Issues, https://github.com/philgyford/django-ditto/issues
Project-URL: Source Code, https://github.com/philgyford/django-ditto
Keywords: ditto,twitter,flickr,pinboard,last.fm
Classifier: Development Status :: 5 - Production/Stable
Classifier: Environment :: Web Environment
Classifier: Framework :: Django
Classifier: Framework :: Django :: 4.2
Classifier: Framework :: Django :: 5.1
Classifier: Framework :: Django :: 5.2
Classifier: Intended Audience :: Developers
Classifier: License :: OSI Approved :: MIT License
Classifier: Natural Language :: English
Classifier: Operating System :: OS Independent
Classifier: Programming Language :: Python
Classifier: Programming Language :: Python :: 3 :: Only
Classifier: Programming Language :: Python :: 3.10
Classifier: Programming Language :: Python :: 3.11
Classifier: Programming Language :: Python :: 3.12
Classifier: Programming Language :: Python :: 3.13
Classifier: Programming Language :: Python :: 3.14
Classifier: Topic :: Internet :: WWW/HTTP
Classifier: Topic :: Internet :: WWW/HTTP :: Dynamic Content
Classifier: Topic :: Software Development :: Libraries
Classifier: Topic :: Software Development :: Libraries :: Python Modules
Requires-Python: >=3.10
License-File: LICENSE
Requires-Dist: django-imagekit<7.0,>=5.0
Requires-Dist: django-sortedm2m<5.0,>=4.0
Requires-Dist: django-taggit<7.0,>=5.0.0
Requires-Dist: flickrapi<2.5,>=2.4
Requires-Dist: pillow<13.0,>=10.0.0
Requires-Dist: twitter-text-python<1.2,>=1.1.1
Requires-Dist: twython<3.10,>=3.7.0
Dynamic: license-file
